pynanoid-0.1.1.dist-info/RECORD
pynanoid-0.1.1.dist-info/METADATA
pynanoid-0.1.1.dist-info/WHEEL
pynanoid-0.1.1.dist-info/licenses/LICENSE
pynanoid/_pynanoid.pypy310-pp73-x86-linux-gnu.so
pynanoid/constants.py
pynanoid/__init__.py
pynanoid/nanoid.py
pynanoid/_pynanoid.pyi
pynanoid/py.typed
