Metadata-Version: 2.3
Name: pynanoid
Version: 0.1.1
Classifier: Intended Audience :: Developers
Classifier: Programming Language :: Rust
Classifier: Programming Language :: Python :: Implementation :: CPython
Classifier: Programming Language :: Python :: Implementation :: PyPy
Classifier: Programming Language :: Python :: 3
Classifier: Programming Language :: Python :: 3 :: Only
Classifier: Programming Language :: Python :: 3.9
Classifier: Programming Language :: Python :: 3.10
Classifier: Programming Language :: Python :: 3.11
Classifier: Programming Language :: Python :: 3.12
Classifier: Programming Language :: Python :: 3.13
Classifier: Operating System :: OS Independent
Classifier: License :: OSI Approved :: MIT License
Classifier: Typing :: Typed
License-File: LICENSE
License-File: LICENSE
Summary: A tiny, secure, URL-friendly, unique string ID generator for Python written in Rust
Author-email: Arunanshu Biswas <mydellpc07@gmail.com>
Requires-Python: >=3.9
Project-URL: repository, https://github.com/arunanshub/pynanoid
Project-URL: Bug Tracker, https://github.com/arunanshub/pynanoid/issues
